<something>
	<exp id="1" ExpLevelUp="400" Physique="10" />
	<exp id="2" ExpLevelUp="600" Physique="11" />
	<exp id="3" ExpLevelUp="900" Physique="11" />
	<exp id="4" ExpLevelUp="1300" Physique="12" />
	<exp id="5" ExpLevelUp="1600" Physique="12" />
	<exp id="6" ExpLevelUp="2100" Physique="13" />
	<exp id="7" ExpLevelUp="2500" Physique="13" />
	<exp id="8" ExpLevelUp="3000" Physique="14" />
	<exp id="9" ExpLevelUp="3600" Physique="15" />
	<exp id="10" ExpLevelUp="4100" Physique="15" />
	<exp id="11" ExpLevelUp="4800" Physique="16" />
	<exp id="12" ExpLevelUp="5400" Physique="16" />
	<exp id="13" ExpLevelUp="6100" Physique="17" />
	<exp id="14" ExpLevelUp="6900" Physique="18" />
	<exp id="15" ExpLevelUp="7600" Physique="18" />
	<exp id="16" ExpLevelUp="8500" Physique="19" />
	<exp id="17" ExpLevelUp="9300" Physique="19" />
	<exp id="18" ExpLevelUp="10200" Physique="20" />
	<exp id="19" ExpLevelUp="11200" Physique="21" />
	<exp id="20" ExpLevelUp="13000" Physique="22" />
	<exp id="21" ExpLevelUp="15000" Physique="22" />
	<exp id="22" ExpLevelUp="17300" Physique="23" />
	<exp id="23" ExpLevelUp="19800" Physique="24" />
	<exp id="24" ExpLevelUp="22400" Physique="25" />
	<exp id="25" ExpLevelUp="25200" Physique="26" />
	<exp id="26" ExpLevelUp="28100" Physique="27" />
	<exp id="27" ExpLevelUp="31200" Physique="28" />
	<exp id="28" ExpLevelUp="34400" Physique="28" />
	<exp id="29" ExpLevelUp="37800" Physique="29" />
	<exp id="30" ExpLevelUp="41300" Physique="30" />
	<exp id="31" ExpLevelUp="48600" Physique="31" />
	<exp id="32" ExpLevelUp="56200" Physique="32" />
	<exp id="33" ExpLevelUp="64300" Physique="33" />
	<exp id="34" ExpLevelUp="72700" Physique="34" />
	<exp id="35" ExpLevelUp="81600" Physique="35" />
	<exp id="36" ExpLevelUp="90800" Physique="36" />
	<exp id="37" ExpLevelUp="100400" Physique="37" />
	<exp id="38" ExpLevelUp="110400" Physique="38" />
	<exp id="39" ExpLevelUp="120800" Physique="39" />
	<exp id="40" ExpLevelUp="131600" Physique="40" />
	<exp id="41" ExpLevelUp="154800" Physique="41" />
	<exp id="42" ExpLevelUp="181800" Physique="43" />
	<exp id="43" ExpLevelUp="210600" Physique="44" />
	<exp id="44" ExpLevelUp="240900" Physique="45" />
	<exp id="45" ExpLevelUp="273000" Physique="47" />
	<exp id="46" ExpLevelUp="306600" Physique="48" />
	<exp id="47" ExpLevelUp="342000" Physique="50" />
	<exp id="48" ExpLevelUp="378900" Physique="51" />
	<exp id="49" ExpLevelUp="417600" Physique="52" />
	<exp id="50" ExpLevelUp="470200" Physique="54" />
	<exp id="51" ExpLevelUp="525300" Physique="55" />
	<exp id="52" ExpLevelUp="582700" Physique="57" />
	<exp id="53" ExpLevelUp="642600" Physique="58" />
	<exp id="54" ExpLevelUp="704800" Physique="60" />
	<exp id="55" ExpLevelUp="769500" Physique="61" />
	<exp id="56" ExpLevelUp="836500" Physique="63" />
	<exp id="57" ExpLevelUp="906000" Physique="64" />
	<exp id="58" ExpLevelUp="977800" Physique="66" />
	<exp id="59" ExpLevelUp="1052100" Physique="68" />
	<exp id="60" ExpLevelUp="1144500" Physique="69" />
	<exp id="61" ExpLevelUp="1204500" Physique="71" />
	<exp id="62" ExpLevelUp="1265900" Physique="74" />
	<exp id="63" ExpLevelUp="1328500" Physique="76" />
	<exp id="64" ExpLevelUp="1392500" Physique="78" />
	<exp id="65" ExpLevelUp="1457700" Physique="80" />
	<exp id="66" ExpLevelUp="1524100" Physique="82" />
	<exp id="67" ExpLevelUp="1591900" Physique="84" />
	<exp id="68" ExpLevelUp="1660900" Physique="86" />
	<exp id="69" ExpLevelUp="1731300" Physique="88" />
	<exp id="70" ExpLevelUp="1802900" Physique="90" />
	<exp id="71" ExpLevelUp="1875700" Physique="92" />
	<exp id="72" ExpLevelUp="1949900" Physique="94" />
	<exp id="73" ExpLevelUp="2025300" Physique="97" />
	<exp id="74" ExpLevelUp="2102100" Physique="99" />
	<exp id="75" ExpLevelUp="2180100" Physique="101" />
	<exp id="76" ExpLevelUp="2259300" Physique="103" />
	<exp id="77" ExpLevelUp="2339900" Physique="105" />
	<exp id="78" ExpLevelUp="2421700" Physique="107" />
	<exp id="79" ExpLevelUp="2504900" Physique="110" />
	<exp id="80" ExpLevelUp="2616700" Physique="112" />
	<exp id="81" ExpLevelUp="2730400" Physique="115" />
	<exp id="82" ExpLevelUp="2846000" Physique="118" />
	<exp id="83" ExpLevelUp="2963600" Physique="120" />
	<exp id="84" ExpLevelUp="3083100" Physique="123" />
	<exp id="85" ExpLevelUp="3204500" Physique="125" />
	<exp id="86" ExpLevelUp="3327800" Physique="127" />
	<exp id="87" ExpLevelUp="3453000" Physique="130" />
	<exp id="88" ExpLevelUp="3580200" Physique="132" />
	<exp id="89" ExpLevelUp="3709300" Physique="134" />
	<exp id="90" ExpLevelUp="3840300" Physique="137" />
	<exp id="91" ExpLevelUp="3973200" Physique="139" />
	<exp id="92" ExpLevelUp="4108000" Physique="141" />
	<exp id="93" ExpLevelUp="4244800" Physique="144" />
	<exp id="94" ExpLevelUp="4383500" Physique="146" />
	<exp id="95" ExpLevelUp="4524100" Physique="148" />
	<exp id="96" ExpLevelUp="4666600" Physique="151" />
	<exp id="97" ExpLevelUp="4811000" Physique="153" />
	<exp id="98" ExpLevelUp="4957400" Physique="155" />
	<exp id="99" ExpLevelUp="5105700" Physique="158" />
	<exp id="100" ExpLevelUp="5255900" Physique="160" />
</something>